odoo10_addon_barcodes_generator_product-10.0.1.0.0-py2.7-nspkg.pth
odoo/addons/barcodes_generator_product/README.rst
odoo/addons/barcodes_generator_product/__init__.py
odoo/addons/barcodes_generator_product/__manifest__.py
odoo/addons/barcodes_generator_product/demo/barcode_rule.xml
odoo/addons/barcodes_generator_product/demo/function.xml
odoo/addons/barcodes_generator_product/demo/product.xml
odoo/addons/barcodes_generator_product/demo/res_users.xml
odoo/addons/barcodes_generator_product/i18n/fr.po
odoo/addons/barcodes_generator_product/models/__init__.py
odoo/addons/barcodes_generator_product/models/barcode_rule.py
odoo/addons/barcodes_generator_product/models/product_product.py
odoo/addons/barcodes_generator_product/models/product_template.py
odoo/addons/barcodes_generator_product/static/description/icon.png
odoo/addons/barcodes_generator_product/static/description/product_template_manual_generation.png
odoo/addons/barcodes_generator_product/tests/__init__.py
odoo/addons/barcodes_generator_product/tests/test_barcodes_generator_product.py
odoo/addons/barcodes_generator_product/views/view_product_product.xml
odoo/addons/barcodes_generator_product/views/view_product_template.xml
odoo10_addon_barcodes_generator_product-10.0.1.0.0.dist-info/DESCRIPTION.rst
odoo10_addon_barcodes_generator_product-10.0.1.0.0.dist-info/METADATA
odoo10_addon_barcodes_generator_product-10.0.1.0.0.dist-info/RECORD
odoo10_addon_barcodes_generator_product-10.0.1.0.0.dist-info/WHEEL
odoo10_addon_barcodes_generator_product-10.0.1.0.0.dist-info/metadata.json
odoo10_addon_barcodes_generator_product-10.0.1.0.0.dist-info/namespace_packages.txt
odoo10_addon_barcodes_generator_product-10.0.1.0.0.dist-info/top_level.txt
